README.md
setup.cfg
setup.py
bin/capture-interface.py
bin/get-metadata.py
bin/get-route-table.py
bin/get-stat-drop.py
bin/load-bin-from-s3.py
bin/load-config-from-s3.py
bin/measure-packet-trace.py
bin/monitor-vpn.py
bin/save-config-to-s3.py
bin/save-tech-support-to-s3.py
csr_aws_guestshell/__init__.py
csr_aws_guestshell/csr_aws_guestshell.py
csr_aws_guestshell.egg-info/PKG-INFO
csr_aws_guestshell.egg-info/SOURCES.txt
csr_aws_guestshell.egg-info/dependency_links.txt
csr_aws_guestshell.egg-info/requires.txt
csr_aws_guestshell.egg-info/top_level.txt