Metadata-Version: 1.1
Name: csr-aws-guestshell
Version: 0.0.19.dev0
Summary: A helper library for Cisco guestshell on AWS
Home-page: https://github.com/CiscoDevNet/csr_aws_guestshell
Author: Christopher Reder
Author-email: creder@cisco.com
License: MIT
Download-URL: https://github.com/CiscoDevNet/csr_aws_guestshell/archive/0.0.19.dev.tar.gz
Keywords: cisco,aws,guestshell
Platform: UNKNOWN
